deciplot.py
deciplot-0.0.1.dist-info/LICENSE.txt
deciplot-0.0.1.dist-info/METADATA
deciplot-0.0.1.dist-info/WHEEL
deciplot-0.0.1.dist-info/top_level.txt
deciplot-0.0.1.dist-info/RECORD
