Metadata-Version: 2.1
Name: deciplot
Version: 0.0.1
Summary: A handy tool that helps you better visualize your data by plotting 2D decision boundaries, using any sklearn classifier models.
Home-page: https://github.com/hxt365/Deciplot
Author: Truong Hoang
Author-email: hxt365@gmail.com
License: UNKNOWN
Platform: UNKNOWN
Classifier: Programming Language :: Python :: 3
Classifier: Programming Language :: Python :: 3.6
Classifier: Programming Language :: Python :: 3.7
Classifier: Programming Language :: Python :: 3.8
Classifier: Programming Language :: Python :: 3.9
Classifier: Operating System :: OS Independent
Requires-Dist: numpy (>=1.15)
Requires-Dist: sklearn
Requires-Dist: matplotlib (>=3.0)
